glif/__init__.py
glif/__main__.py
glif-0.15.dist-info/entry_points.txt
glif-0.15.dist-info/LICENSE
glif-0.15.dist-info/WHEEL
glif-0.15.dist-info/METADATA
glif-0.15.dist-info/RECORD
