Metadata-Version: 2.1
Name: glif
Version: 0.15
Summary: CLI tool for creating gifs from a glob pattern
License: MIT
Author: Andy Jackson
Author-email: amjack100@gmail.com
Requires-Python: >=3.7
Classifier: License :: OSI Approved :: MIT License
Classifier: Programming Language :: Python :: 3
Classifier: Programming Language :: Python :: 3.7
Classifier: Programming Language :: Python :: 3.8
Classifier: Programming Language :: Python :: 3.9
Requires-Dist: click (>=7.1.2,<8.0.0)
Requires-Dist: imageio (>=2.9.0,<3.0.0)
